tigrbl_client/__init__.py
tigrbl_client/_crud.py
tigrbl_client/_nested_crud.py
tigrbl_client/_rpc.py
tigrbl_client-0.2.0.dev4.dist-info/LICENSE
tigrbl_client-0.2.0.dev4.dist-info/METADATA
tigrbl_client-0.2.0.dev4.dist-info/WHEEL
tigrbl_client-0.2.0.dev4.dist-info/RECORD
