Metadata-Version: 2.3
Name: tigrbl-client
Version: 0.2.0.dev4
Summary: A client for Tigrbl servers by Swarmauri.
License: Apache-2.0
Author: Swarmauri Team
Author-email: team@swarmauri.com
Requires-Python: >=3.10,<3.13
Classifier: License :: OSI Approved :: Apache Software License
Classifier: Development Status :: 3 - Alpha
Classifier: Programming Language :: Python :: 3.10
Classifier: Programming Language :: Python :: 3.11
Classifier: Programming Language :: Python :: 3.12
Requires-Dist: fastapi (>=0.100.0)
Requires-Dist: pydantic (>=2.0.0)
Requires-Dist: swarmauri_base
Requires-Dist: swarmauri_core
Requires-Dist: swarmauri_standard
